youtube/__init__.py
youtube/api.py
youtube/baseelement.py
youtube/baseparser.py
youtube/cache.py
youtube/channelsearchparser.py
youtube/errors.py
youtube/http_fetcher.py
youtube/playlist.py
youtube/playlistpageparser.py
youtube/playlistsearchparser.py
youtube/search.py
youtube/signatures.py
youtube/tools.py
youtube/video.py
youtube/videopageparser.py
youtube/videosearchparser.py
yt_info-0.0.1.dist-info/DESCRIPTION.rst
yt_info-0.0.1.dist-info/METADATA
yt_info-0.0.1.dist-info/RECORD
yt_info-0.0.1.dist-info/WHEEL
yt_info-0.0.1.dist-info/metadata.json
yt_info-0.0.1.dist-info/top_level.txt
